dlprgs/__init__.py
dlprgs/log.py
dlprgs/data/1.txt
dlprgs/data/2.txt
dlprgs/data/3.txt
dlprgs/data/4.txt
dlprgs/data/5.txt
dlprgs/data/__init__.py
dlprgs-0.1.9.dist-info/METADATA
dlprgs-0.1.9.dist-info/WHEEL
dlprgs-0.1.9.dist-info/top_level.txt
dlprgs-0.1.9.dist-info/RECORD
