Metadata-Version: 2.4
Name: dlprgs
Version: 0.1.9
Summary: Add your description here
Requires-Python: >=3.12
Requires-Dist: build>=1.4.0
Requires-Dist: twine>=6.2.0
